setup.py
lightbar/__init__.py
lightbar/lightbar.py
lightbar.egg-info/PKG-INFO
lightbar.egg-info/SOURCES.txt
lightbar.egg-info/dependency_links.txt
lightbar.egg-info/not-zip-safe
lightbar.egg-info/top_level.txt