Metadata-Version: 1.0
Name: lightbar
Version: 0.1
Summary: Simple progress bar for Python 3
Home-page: http://github.com/wzhliang/lightbar
Author: Wenzhi Liang
Author-email: wenzhi.liang@gmail.com
License: MIT
Platform: UNKNOWN
